minitrade/admin/Home.py
minitrade/admin/pages/1_Trading.py
minitrade/admin/pages/2_Strategy.py
minitrade/admin/pages/3_Datasource.py
minitrade/admin/pages/4_Broker.py
minitrade/admin/pages/5_Task.py
minitrade/admin/pages/6_Log.py
minitrade/admin/pages/7_Settings.py
minitrade/admin/pages/8_Fred.py
minitrade/backtest/__init__.py
minitrade/backtest/core/__init__.py
minitrade/backtest/core/_plotting.py
minitrade/backtest/core/_stats.py
minitrade/backtest/core/_util.py
minitrade/backtest/core/autoscale_cb.js
minitrade/backtest/core/backtesting.py
minitrade/backtest/core/lib.py
minitrade/backtest/core/test/EURUSD.csv
minitrade/backtest/core/test/GOOG.csv
minitrade/backtest/core/test/__init__.py
minitrade/backtest/core/test/__main__.py
minitrade/backtest/core/test/_test.py
minitrade/backtest/utils.py
minitrade/broker/__init__.py
minitrade/broker/base.py
minitrade/broker/ib.py
minitrade/broker/ibgateway.py
minitrade/broker/manual.py
minitrade/cli.py
minitrade/datasource/__init__.py
minitrade/datasource/alpaca.py
minitrade/datasource/base.py
minitrade/datasource/cboe_futures.py
minitrade/datasource/cboe_index.py
minitrade/datasource/eastmoney.py
minitrade/datasource/eodhd.py
minitrade/datasource/ib.py
minitrade/datasource/tiingo.py
minitrade/datasource/twelve.py
minitrade/datasource/union.py
minitrade/datasource/yahoo.py
minitrade/trader/__init__.py
minitrade/trader/scheduler.py
minitrade/trader/schema/0.1.28.sql
minitrade/trader/schema/0.1.29.sql
minitrade/trader/schema/0.1.30.sql
minitrade/trader/schema/0.1.32.sql
minitrade/trader/schema/0.1.34.sql
minitrade/trader/schema/0.1.36.sql
minitrade/trader/schema/consolidated.sql
minitrade/trader/trader.py
minitrade/utils/config.py
minitrade/utils/mailjet.py
minitrade/utils/mtdb.py
minitrade/utils/telegram.py
minitrade-0.1.40.dist-info/LICENSE.md
minitrade-0.1.40.dist-info/METADATA
minitrade-0.1.40.dist-info/WHEEL
minitrade-0.1.40.dist-info/entry_points.txt
minitrade-0.1.40.dist-info/RECORD
